retrowrapper.py
retrowrapper-0.3.0.dist-info/LICENSE
retrowrapper-0.3.0.dist-info/METADATA
retrowrapper-0.3.0.dist-info/WHEEL
retrowrapper-0.3.0.dist-info/top_level.txt
retrowrapper-0.3.0.dist-info/RECORD
