Metadata-Version: 2.1
Name: retrowrapper
Version: 0.3.0
Summary: Wrapper for OpenAI Retro Gym environments to allow multiple processes.
Home-page: https://github.com/MaxStrange/retrowrapper
Author: Max Strange
Author-email: maxfieldstrange@gmail.com
License: MIT
Keywords: reinforcement-learning retro ai rl dl deep-learning gym openai
Platform: UNKNOWN
Classifier: Development Status :: 3 - Alpha
Classifier: Intended Audience :: Developers
Classifier: License :: OSI Approved :: MIT License
Classifier: Operating System :: OS Independent
Classifier: Programming Language :: Python
Classifier: Programming Language :: Python :: 3
Classifier: Programming Language :: Python :: 3.4
Classifier: Programming Language :: Python :: 3.5
Classifier: Programming Language :: Python :: 3.6
Classifier: Programming Language :: Python :: 3.7
Requires-Python: ~=3.4
Requires-Dist: gym-retro
